libsasscompiler/__init__.py
libsasscompiler/version.py
libsasscompiler-0.2.0.dist-info/AUTHORS
libsasscompiler-0.2.0.dist-info/LICENSE.md
libsasscompiler-0.2.0.dist-info/METADATA
libsasscompiler-0.2.0.dist-info/WHEEL
libsasscompiler-0.2.0.dist-info/top_level.txt
libsasscompiler-0.2.0.dist-info/RECORD
