Metadata-Version: 2.1
Name: libsasscompiler
Version: 0.2.0
Summary: django pipeline scss/sass compiler, no needed of ruby
Home-page: https://github.com/sonic182/libsasscompiler
Author: Johanderson Mogollon
Author-email: johanderson@mogollon.com.ve
License: MIT
Requires-Python: >=3.6.0
License-File: LICENSE.md
License-File: AUTHORS
Requires-Dist: django-pipeline ==3.1.0
Requires-Dist: libsass ==0.23.0
Provides-Extra: test
Requires-Dist: django ==2.2.28 ; extra == 'test'
Requires-Dist: django-pipeline ==3.1.0 ; extra == 'test'
Requires-Dist: iniconfig ==2.0.0 ; extra == 'test'
Requires-Dist: packaging ==24.1 ; extra == 'test'
Requires-Dist: pluggy ==1.5.0 ; extra == 'test'
Requires-Dist: pytest ==8.3.2 ; extra == 'test'
Requires-Dist: pytest-cov ==5.0.0 ; extra == 'test'
Requires-Dist: pytz ==2024.1 ; extra == 'test'
Requires-Dist: sqlparse ==0.5.1 ; extra == 'test'
